neucodec/__init__.py
neucodec/activations.py
neucodec/alias_free_torch/__init__.py
neucodec/alias_free_torch/act.py
neucodec/alias_free_torch/filter.py
neucodec/alias_free_torch/resample.py
neucodec/bs_roformer5.py
neucodec/codec_decoder_vocos.py
neucodec/codec_encoder.py
neucodec/codec_encoder_distill.py
neucodec/distill_layers.py
neucodec/model.py
neucodec/module.py
neucodec/tconv/__init__.py
neucodec/tconv/base.py
neucodec/tconv/t_first.py
neucodec-0.0.4.dist-info/METADATA
neucodec-0.0.4.dist-info/WHEEL
neucodec-0.0.4.dist-info/licenses/LICENSE
neucodec-0.0.4.dist-info/RECORD
