Metadata-Version: 2.4
Name: neucodec
Version: 0.0.4
Summary: A package for NeuCodec, based on xcodec2.
License: MIT
License-File: LICENSE
Author: Neuphonic
Author-email: support@neuphonic.com
Requires-Python: >=3.10,<4.0
Classifier: License :: OSI Approved :: MIT License
Classifier: Programming Language :: Python :: 3
Classifier: Programming Language :: Python :: 3.10
Classifier: Programming Language :: Python :: 3.11
Classifier: Programming Language :: Python :: 3.12
Classifier: Programming Language :: Python :: 3.13
Classifier: Programming Language :: Python :: 3.14
Requires-Dist: local_attention (>=1.11.1)
Requires-Dist: numpy (>=2.0.2)
Requires-Dist: torch (>=2.5.1)
Requires-Dist: torchao (>=0.12.0)
Requires-Dist: torchaudio (>=2.5.1)
Requires-Dist: torchtune (>=0.3.1)
Requires-Dist: transformers (>=4.44.2)
Requires-Dist: vector-quantize-pytorch (==1.17.8)
